rpa_test_zhang/__about__.py
rpa_test_zhang/__init__.py
rpa_test_zhang/test.py
rpa_test-0.2.1.dist-info/METADATA
rpa_test-0.2.1.dist-info/WHEEL
rpa_test-0.2.1.dist-info/licenses/LICENSE.txt
rpa_test-0.2.1.dist-info/RECORD
