Metadata-Version: 2.1
Name: rpa-test
Version: 0.2.1
Summary: test yingdao rpa installation python package
Project-URL: Documentation, https://github.com/unknown/rpa-test-zhang#readme
Project-URL: Issues, https://github.com/unknown/rpa-test-zhang/issues
Project-URL: Source, https://github.com/unknown/rpa-test-zhang
Author-email: zhang <428162626@qq.com>
License-Expression: MIT
License-File: LICENSE.txt
Classifier: Development Status :: 4 - Beta
Classifier: Programming Language :: Python
Classifier: Programming Language :: Python :: 3.7
Classifier: Programming Language :: Python :: 3.8
Classifier: Programming Language :: Python :: 3.9
Classifier: Programming Language :: Python :: 3.10
Classifier: Programming Language :: Python :: 3.11
Classifier: Programming Language :: Python :: Implementation :: CPython
Classifier: Programming Language :: Python :: Implementation :: PyPy
Requires-Python: >=3.7
Requires-Dist: requests==2.27.1
